kappabenchmark/__init__.py
kappabenchmark/dataloading.py
kappabenchmark/dataloading_benchmarks.py
kappabenchmark/run.py
kappabenchmark/scripts/__init__.py
kappabenchmark/scripts/main_benchmark_grid.py
kappabenchmark-0.0.10.dist-info/LICENSE
kappabenchmark-0.0.10.dist-info/METADATA
kappabenchmark-0.0.10.dist-info/WHEEL
kappabenchmark-0.0.10.dist-info/top_level.txt
kappabenchmark-0.0.10.dist-info/RECORD
