Metadata-Version: 2.1
Name: kappabenchmark
Version: 0.0.10
Summary: pytorch dataset wrappers for in-memory caching
Home-page: https://github.com/BenediktAlkin/KappaBenchmark
Project-URL: Source Code, https://github.com/BenediktAlkin/KappaBenchmark
Project-URL: Bug Tracker, https://github.com/BenediktAlkin/KappaBenchmark/issues
Classifier: Programming Language :: Python :: 3
Classifier: License :: OSI Approved :: MIT License
Classifier: Operating System :: OS Independent
Requires-Python: >=3.6
License-File: LICENSE
Requires-Dist: torch
Requires-Dist: torchvision
Requires-Dist: kappadata
Requires-Dist: kappaprofiler
Requires-Dist: pytorch-concurrent-dataloader
